

{
  "settingsReloadIntervalMinutes": 1,
  "fullscreen": true,
  "autoStart": true,
  "lazyLoadTabs": false,
  "closeExistingTabs": true,
  "websites": [
    {
      "url": "https://analytics.ringcentral.co.uk/full/live-reports/461192067-466631067-144b5286-de69-42b8-921c-7f63a2985b7d",
      "duration": 100,
      "tabReloadIntervalSeconds": 15000
    },
    {
      "url": "https://raw.githubusercontent.com/EQL-IT/EQL-WB/main/Star1.jpg",
      "duration": 25,
      "tabReloadIntervalSeconds": 12.5
    },
  {
      "url": "https://raw.githubusercontent.com/EQL-IT/EQL-WB/main/Star2.jpg",
      "duration": 25,
      "tabReloadIntervalSeconds": 12.5
    },
    {
      "url": "https://raw.githubusercontent.com/EQL-IT/EQL-WB/main/Star3A.jpg",
      "duration": 25,
      "tabReloadIntervalSeconds": 12.5
    },
  {
      "url": "https://raw.githubusercontent.com/EQL-IT/EQL-WB/main/Star3B.jpg",
      "duration": 25,
      "tabReloadIntervalSeconds": 12.5
    },
  {
      "url": "https://raw.githubusercontent.com/EQL-IT/EQL-WB/main/Star4.jpg",
      "duration": 25,
      "tabReloadIntervalSeconds": 12.5
    },
  {
      "url": "https://raw.githubusercontent.com/EQL-IT/EQL-WB/main/StarT.jpg",
      "duration": 25,
      "tabReloadIntervalSeconds": 12.5
    },
     {
      "url": "https://equilaw.freshstatus.io/",
      "duration": 20,
      "tabReloadIntervalSeconds": 12.5
    },
  {
      "url": "https://raw.githubusercontent.com/EQL-IT/EQL-WB/main/Welcome.jpg",
      "duration": 45,
      "tabReloadIntervalSeconds": 25
    },
 {
      "url": "file:///C:/amzn2.mp4",
      "duration": 25,
      "tabReloadIntervalSeconds": 15
    }

  ]
}
